skeletor/__init__.py
skeletor/utilities.py
skeletor/data/722817260.obj
skeletor/data/README.md
skeletor/data/__init__.py
skeletor/post/__init__.py
skeletor/post/postprocessing.py
skeletor/post/radiusextraction.py
skeletor/pre/__init__.py
skeletor/pre/meshcontraction.py
skeletor/pre/preprocessing.py
skeletor/pre/utils.py
skeletor/pre/templates/blender_decimate.py.template
skeletor/pre/templates/blender_remesh.py.template
skeletor/skeletonize/__init__.py
skeletor/skeletonize/base.py
skeletor/skeletonize/edge_collapse.py
skeletor/skeletonize/tangent_ball.py
skeletor/skeletonize/teasar.py
skeletor/skeletonize/utils.py
skeletor/skeletonize/vertex_cluster.py
skeletor/skeletonize/wave.py
skeletor-1.3.0.dist-info/LICENSE
skeletor-1.3.0.dist-info/METADATA
skeletor-1.3.0.dist-info/WHEEL
skeletor-1.3.0.dist-info/top_level.txt
skeletor-1.3.0.dist-info/RECORD
