Metadata-Version: 2.1
Name: skeletor
Version: 1.3.0
Summary: Python 3 library to extract skeletons from 3D meshes
Home-page: https://github.com/navis-org/skeletor
Author: Philipp Schlegel
Author-email: pms70@cam.ac.uk
License: GNU GPL V3
Project-URL: Documentation, https://navis-org.github.io/skeletor/
Project-URL: Source, https://github.com/navis-org/skeletor
Project-URL: Changelog, https://github.com/navis-org/skeletor/blob/master/NEWS.md
Keywords: mesh skeletonization mesh contraction skeleton extraction
Classifier: Development Status :: 4 - Beta
Classifier: Intended Audience :: Science/Research
Classifier: Topic :: Scientific/Engineering :: Bio-Informatics
Classifier: License :: OSI Approved :: GNU General Public License v3 or later (GPLv3+)
Classifier: Programming Language :: Python :: 3
Classifier: Programming Language :: Python :: 3.7
Classifier: Programming Language :: Python :: 3.8
Classifier: Programming Language :: Python :: 3.9
Requires-Python: >=3.6
License-File: LICENSE
Requires-Dist: numpy>=1.16.0
Requires-Dist: trimesh>=2.38.0
Requires-Dist: tqdm>=4.50.0
Requires-Dist: scipy>=1.3.0
Requires-Dist: pandas>=0.24.2
Requires-Dist: networkx>=2.4
Requires-Dist: scikit-learn>=0.23
Requires-Dist: igraph>=0.8
Requires-Dist: ncollpyde>=0.14.0
